melon.py
melon_chart.py-1.0.0.dist-info/LICENSE
melon_chart.py-1.0.0.dist-info/METADATA
melon_chart.py-1.0.0.dist-info/WHEEL
melon_chart.py-1.0.0.dist-info/top_level.txt
melon_chart.py-1.0.0.dist-info/RECORD
